<annotation>
	<folder>Images</folder>
	<filename>Invoice_100009_scaleBlurRotate3.PNG</filename>
	<path>/home/pawel/PracaLocal/PRACA_LOCAL/OCR_AI/ocr-ai-preprocessing/SetUp_Manual_01/models/research/object_detection/synthDataAug/Images/Invoice_100009_scaleBlurRotate3.PNG</path>
	<source>
		<database>Unknown</database>
	</source>
	<size>
		<width>794</width>
		<height>1123</height>
		<depth>3</depth>
	</size>
	<segmented>0</segmented>
	<object>
		<name>TextBox</name>
		<pose>Unspecified</pose>
		<truncated>0</truncated>
		<difficult>0</difficult>
		<bndbox>
			<xmin>70</xmin>
			<ymin>74</ymin>
			<xmax>366</xmax>
			<ymax>162</ymax>
		</bndbox>
	</object>
	<object>
		<name>TextBox</name>
		<pose>Unspecified</pose>
		<truncated>0</truncated>
		<difficult>0</difficult>
		<bndbox>
			<xmin>480</xmin>
			<ymin>72</ymin>
			<xmax>704</xmax>
			<ymax>103</ymax>
		</bndbox>
	</object>
	<object>
		<name>TextBox</name>
		<pose>Unspecified</pose>
		<truncated>0</truncated>
		<difficult>0</difficult>
		<bndbox>
			<xmin>416</xmin>
			<ymin>101</ymin>
			<xmax>570</xmax>
			<ymax>130</ymax>
		</bndbox>
	</object>
	<object>
		<name>TextBox</name>
		<pose>Unspecified</pose>
		<truncated>0</truncated>
		<difficult>0</difficult>
		<bndbox>
			<xmin>636</xmin>
			<ymin>113</ymin>
			<xmax>731</xmax>
			<ymax>137</ymax>
		</bndbox>
	</object>
	<object>
		<name>TextBox</name>
		<pose>Unspecified</pose>
		<truncated>0</truncated>
		<difficult>0</difficult>
		<bndbox>
			<xmin>414</xmin>
			<ymin>142</ymin>
			<xmax>521</xmax>
			<ymax>165</ymax>
		</bndbox>
	</object>
	<object>
		<name>TextBox</name>
		<pose>Unspecified</pose>
		<truncated>0</truncated>
		<difficult>0</difficult>
		<bndbox>
			<xmin>635</xmin>
			<ymin>153</ymin>
			<xmax>717</xmax>
			<ymax>174</ymax>
		</bndbox>
	</object>
	<object>
		<name>TextBox</name>
		<pose>Unspecified</pose>
		<truncated>0</truncated>
		<difficult>0</difficult>
		<bndbox>
			<xmin>430</xmin>
			<ymin>180</ymin>
			<xmax>647</xmax>
			<ymax>209</ymax>
		</bndbox>
	</object>
	<object>
		<name>TextBox</name>
		<pose>Unspecified</pose>
		<truncated>0</truncated>
		<difficult>0</difficult>
		<bndbox>
			<xmin>238</xmin>
			<ymin>207</ymin>
			<xmax>690</xmax>
			<ymax>265</ymax>
		</bndbox>
	</object>
	<object>
		<name>TextBox</name>
		<pose>Unspecified</pose>
		<truncated>0</truncated>
		<difficult>0</difficult>
		<bndbox>
			<xmin>73</xmin>
			<ymin>194</ymin>
			<xmax>204</xmax>
			<ymax>219</ymax>
		</bndbox>
	</object>
	<object>
		<name>TextBox</name>
		<pose>Unspecified</pose>
		<truncated>0</truncated>
		<difficult>0</difficult>
		<bndbox>
			<xmin>65</xmin>
			<ymin>279</ymin>
			<xmax>321</xmax>
			<ymax>378</ymax>
		</bndbox>
	</object>
	<object>
		<name>TextBox</name>
		<pose>Unspecified</pose>
		<truncated>0</truncated>
		<difficult>0</difficult>
		<bndbox>
			<xmin>433</xmin>
			<ymin>286</ymin>
			<xmax>761</xmax>
			<ymax>392</ymax>
		</bndbox>
	</object>
	<object>
		<name>TextBox</name>
		<pose>Unspecified</pose>
		<truncated>0</truncated>
		<difficult>0</difficult>
		<bndbox>
			<xmin>36</xmin>
			<ymin>772</ymin>
			<xmax>723</xmax>
			<ymax>871</ymax>
		</bndbox>
	</object>
	<object>
		<name>TextBox</name>
		<pose>Unspecified</pose>
		<truncated>0</truncated>
		<difficult>0</difficult>
		<bndbox>
			<xmin>364</xmin>
			<ymin>892</ymin>
			<xmax>692</xmax>
			<ymax>931</ymax>
		</bndbox>
	</object>
	<object>
		<name>TextBox</name>
		<pose>Unspecified</pose>
		<truncated>0</truncated>
		<difficult>0</difficult>
		<bndbox>
			<xmin>274</xmin>
			<ymin>920</ymin>
			<xmax>691</xmax>
			<ymax>959</ymax>
		</bndbox>
	</object>
	<object>
		<name>TextBox</name>
		<pose>Unspecified</pose>
		<truncated>0</truncated>
		<difficult>0</difficult>
		<bndbox>
			<xmin>130</xmin>
			<ymin>989</ymin>
			<xmax>262</xmax>
			<ymax>1014</ymax>
		</bndbox>
	</object>
	<object>
		<name>TextBox</name>
		<pose>Unspecified</pose>
		<truncated>0</truncated>
		<difficult>0</difficult>
		<bndbox>
			<xmin>387</xmin>
			<ymin>983</ymin>
			<xmax>459</xmax>
			<ymax>1008</ymax>
		</bndbox>
	</object>
	<object>
		<name>TextBox</name>
		<pose>Unspecified</pose>
		<truncated>0</truncated>
		<difficult>0</difficult>
		<bndbox>
			<xmin>562</xmin>
			<ymin>1010</ymin>
			<xmax>676</xmax>
			<ymax>1035</ymax>
		</bndbox>
	</object>
	<object>
		<name>TextBox</name>
		<pose>Unspecified</pose>
		<truncated>0</truncated>
		<difficult>0</difficult>
		<bndbox>
			<xmin>61</xmin>
			<ymin>1016</ymin>
			<xmax>309</xmax>
			<ymax>1045</ymax>
		</bndbox>
	</object>
	<object>
		<name>TextBox</name>
		<pose>Unspecified</pose>
		<truncated>0</truncated>
		<difficult>0</difficult>
		<bndbox>
			<xmin>393</xmin>
			<ymin>1032</ymin>
			<xmax>452</xmax>
			<ymax>1050</ymax>
		</bndbox>
	</object>
	<object>
		<name>TextBox</name>
		<pose>Unspecified</pose>
		<truncated>0</truncated>
		<difficult>0</difficult>
		<bndbox>
			<xmin>573</xmin>
			<ymin>1045</ymin>
			<xmax>662</xmax>
			<ymax>1062</ymax>
		</bndbox>
	</object>
	<object>
		<name>Table</name>
		<pose>Unspecified</pose>
		<truncated>0</truncated>
		<difficult>0</difficult>
		<bndbox>
			<xmin>41</xmin>
			<ymin>407</ymin>
			<xmax>757</xmax>
			<ymax>640</ymax>
		</bndbox>
	</object>
	<object>
		<name>Table</name>
		<pose>Unspecified</pose>
		<truncated>0</truncated>
		<difficult>0</difficult>
		<bndbox>
			<xmin>35</xmin>
			<ymin>613</ymin>
			<xmax>342</xmax>
			<ymax>717</ymax>
		</bndbox>
	</object>
	<object>
		<name>Table</name>
		<pose>Unspecified</pose>
		<truncated>0</truncated>
		<difficult>0</difficult>
		<bndbox>
			<xmin>340</xmin>
			<ymin>630</ymin>
			<xmax>745</xmax>
			<ymax>802</ymax>
		</bndbox>
	</object>
</annotation>
