<annotation>
	<folder>Images</folder>
	<filename>Invoice_500013_rotate3_leftRight.PNG</filename>
	<path>/home/pawel/PracaLocal/PRACA_LOCAL/OCR_AI/ocr-ai-preprocessing/SetUp_Manual_01/models/research/object_detection/synthDataAug/Images/Invoice_500013_rotate3_leftRight.PNG</path>
	<source>
		<database>Unknown</database>
	</source>
	<size>
		<width>794</width>
		<height>1123</height>
		<depth>3</depth>
	</size>
	<segmented>0</segmented>
	<object>
		<name>TextBox</name>
		<pose>Unspecified</pose>
		<truncated>0</truncated>
		<difficult>0</difficult>
		<bndbox>
			<xmin>540</xmin>
			<ymin>75</ymin>
			<xmax>769</xmax>
			<ymax>106</ymax>
		</bndbox>
	</object>
	<object>
		<name>TextBox</name>
		<pose>Unspecified</pose>
		<truncated>0</truncated>
		<difficult>0</difficult>
		<bndbox>
			<xmin>74</xmin>
			<ymin>60</ymin>
			<xmax>234</xmax>
			<ymax>99</ymax>
		</bndbox>
	</object>
	<object>
		<name>TextBox</name>
		<pose>Unspecified</pose>
		<truncated>0</truncated>
		<difficult>0</difficult>
		<bndbox>
			<xmin>689</xmin>
			<ymin>153</ymin>
			<xmax>764</xmax>
			<ymax>170</ymax>
		</bndbox>
	</object>
	<object>
		<name>TextBox</name>
		<pose>Unspecified</pose>
		<truncated>0</truncated>
		<difficult>0</difficult>
		<bndbox>
			<xmin>440</xmin>
			<ymin>139</ymin>
			<xmax>647</xmax>
			<ymax>188</ymax>
		</bndbox>
	</object>
	<object>
		<name>TextBox</name>
		<pose>Unspecified</pose>
		<truncated>0</truncated>
		<difficult>0</difficult>
		<bndbox>
			<xmin>72</xmin>
			<ymin>118</ymin>
			<xmax>207</xmax>
			<ymax>140</ymax>
		</bndbox>
	</object>
	<object>
		<name>TextBox</name>
		<pose>Unspecified</pose>
		<truncated>0</truncated>
		<difficult>0</difficult>
		<bndbox>
			<xmin>696</xmin>
			<ymin>261</ymin>
			<xmax>760</xmax>
			<ymax>280</ymax>
		</bndbox>
	</object>
	<object>
		<name>TextBox</name>
		<pose>Unspecified</pose>
		<truncated>0</truncated>
		<difficult>0</difficult>
		<bndbox>
			<xmin>422</xmin>
			<ymin>246</ymin>
			<xmax>640</xmax>
			<ymax>285</ymax>
		</bndbox>
	</object>
	<object>
		<name>TextBox</name>
		<pose>Unspecified</pose>
		<truncated>0</truncated>
		<difficult>0</difficult>
		<bndbox>
			<xmin>68</xmin>
			<ymin>228</ymin>
			<xmax>183</xmax>
			<ymax>248</ymax>
		</bndbox>
	</object>
	<object>
		<name>TextBox</name>
		<pose>Unspecified</pose>
		<truncated>0</truncated>
		<difficult>0</difficult>
		<bndbox>
			<xmin>711</xmin>
			<ymin>336</ymin>
			<xmax>757</xmax>
			<ymax>351</ymax>
		</bndbox>
	</object>
	<object>
		<name>TextBox</name>
		<pose>Unspecified</pose>
		<truncated>0</truncated>
		<difficult>0</difficult>
		<bndbox>
			<xmin>329</xmin>
			<ymin>313</ymin>
			<xmax>634</xmax>
			<ymax>347</ymax>
		</bndbox>
	</object>
	<object>
		<name>Table</name>
		<pose>Unspecified</pose>
		<truncated>0</truncated>
		<difficult>0</difficult>
		<bndbox>
			<xmin>53</xmin>
			<ymin>333</ymin>
			<xmax>760</xmax>
			<ymax>574</ymax>
		</bndbox>
	</object>
	<object>
		<name>Table</name>
		<pose>Unspecified</pose>
		<truncated>0</truncated>
		<difficult>0</difficult>
		<bndbox>
			<xmin>45</xmin>
			<ymin>539</ymin>
			<xmax>408</xmax>
			<ymax>712</ymax>
		</bndbox>
	</object>
	<object>
		<name>TextBox</name>
		<pose>Unspecified</pose>
		<truncated>0</truncated>
		<difficult>0</difficult>
		<bndbox>
			<xmin>299</xmin>
			<ymin>716</ymin>
			<xmax>710</xmax>
			<ymax>769</ymax>
		</bndbox>
	</object>
	<object>
		<name>TextBox</name>
		<pose>Unspecified</pose>
		<truncated>0</truncated>
		<difficult>0</difficult>
		<bndbox>
			<xmin>481</xmin>
			<ymin>863</ymin>
			<xmax>687</xmax>
			<ymax>887</ymax>
		</bndbox>
	</object>
	<object>
		<name>TextBox</name>
		<pose>Unspecified</pose>
		<truncated>0</truncated>
		<difficult>0</difficult>
		<bndbox>
			<xmin>152</xmin>
			<ymin>841</ymin>
			<xmax>348</xmax>
			<ymax>866</ymax>
		</bndbox>
	</object>
	<object>
		<name>TextBox</name>
		<pose>Unspecified</pose>
		<truncated>0</truncated>
		<difficult>0</difficult>
		<bndbox>
			<xmin>369</xmin>
			<ymin>952</ymin>
			<xmax>697</xmax>
			<ymax>982</ymax>
		</bndbox>
	</object>
	<object>
		<name>TextBox</name>
		<pose>Unspecified</pose>
		<truncated>0</truncated>
		<difficult>0</difficult>
		<bndbox>
			<xmin>137</xmin>
			<ymin>983</ymin>
			<xmax>252</xmax>
			<ymax>1001</ymax>
		</bndbox>
	</object>
</annotation>
