<annotation>
	<folder>Images</folder>
	<filename>Invoice_100016_rotate3_leftRight.PNG</filename>
	<path>/home/pawel/PracaLocal/PRACA_LOCAL/OCR_AI/ocr-ai-preprocessing/SetUp_Manual_01/models/research/object_detection/synthDataAug/Images/Invoice_100016_rotate3_leftRight.PNG</path>
	<source>
		<database>Unknown</database>
	</source>
	<size>
		<width>794</width>
		<height>1123</height>
		<depth>3</depth>
	</size>
	<segmented>0</segmented>
	<object>
		<name>TextBox</name>
		<pose>Unspecified</pose>
		<truncated>0</truncated>
		<difficult>0</difficult>
		<bndbox>
			<xmin>465</xmin>
			<ymin>101</ymin>
			<xmax>755</xmax>
			<ymax>182</ymax>
		</bndbox>
	</object>
	<object>
		<name>TextBox</name>
		<pose>Unspecified</pose>
		<truncated>0</truncated>
		<difficult>0</difficult>
		<bndbox>
			<xmin>147</xmin>
			<ymin>55</ymin>
			<xmax>362</xmax>
			<ymax>85</ymax>
		</bndbox>
	</object>
	<object>
		<name>TextBox</name>
		<pose>Unspecified</pose>
		<truncated>0</truncated>
		<difficult>0</difficult>
		<bndbox>
			<xmin>292</xmin>
			<ymin>94</ymin>
			<xmax>426</xmax>
			<ymax>119</ymax>
		</bndbox>
	</object>
	<object>
		<name>TextBox</name>
		<pose>Unspecified</pose>
		<truncated>0</truncated>
		<difficult>0</difficult>
		<bndbox>
			<xmin>114</xmin>
			<ymin>86</ymin>
			<xmax>206</xmax>
			<ymax>110</ymax>
		</bndbox>
	</object>
	<object>
		<name>TextBox</name>
		<pose>Unspecified</pose>
		<truncated>0</truncated>
		<difficult>0</difficult>
		<bndbox>
			<xmin>316</xmin>
			<ymin>134</ymin>
			<xmax>425</xmax>
			<ymax>160</ymax>
		</bndbox>
	</object>
	<object>
		<name>TextBox</name>
		<pose>Unspecified</pose>
		<truncated>0</truncated>
		<difficult>0</difficult>
		<bndbox>
			<xmin>105</xmin>
			<ymin>125</ymin>
			<xmax>206</xmax>
			<ymax>152</ymax>
		</bndbox>
	</object>
	<object>
		<name>TextBox</name>
		<pose>Unspecified</pose>
		<truncated>0</truncated>
		<difficult>0</difficult>
		<bndbox>
			<xmin>196</xmin>
			<ymin>168</ymin>
			<xmax>407</xmax>
			<ymax>197</ymax>
		</bndbox>
	</object>
	<object>
		<name>TextBox</name>
		<pose>Unspecified</pose>
		<truncated>0</truncated>
		<difficult>0</difficult>
		<bndbox>
			<xmin>623</xmin>
			<ymin>221</ymin>
			<xmax>757</xmax>
			<ymax>246</ymax>
		</bndbox>
	</object>
	<object>
		<name>TextBox</name>
		<pose>Unspecified</pose>
		<truncated>0</truncated>
		<difficult>0</difficult>
		<bndbox>
			<xmin>279</xmin>
			<ymin>207</ymin>
			<xmax>591</xmax>
			<ymax>258</ymax>
		</bndbox>
	</object>
	<object>
		<name>TextBox</name>
		<pose>Unspecified</pose>
		<truncated>0</truncated>
		<difficult>0</difficult>
		<bndbox>
			<xmin>447</xmin>
			<ymin>286</ymin>
			<xmax>756</xmax>
			<ymax>414</ymax>
		</bndbox>
	</object>
	<object>
		<name>TextBox</name>
		<pose>Unspecified</pose>
		<truncated>0</truncated>
		<difficult>0</difficult>
		<bndbox>
			<xmin>68</xmin>
			<ymin>275</ymin>
			<xmax>388</xmax>
			<ymax>363</ymax>
		</bndbox>
	</object>
	<object>
		<name>Table</name>
		<pose>Unspecified</pose>
		<truncated>0</truncated>
		<difficult>0</difficult>
		<bndbox>
			<xmin>43</xmin>
			<ymin>408</ymin>
			<xmax>757</xmax>
			<ymax>553</ymax>
		</bndbox>
	</object>
	<object>
		<name>Table</name>
		<pose>Unspecified</pose>
		<truncated>0</truncated>
		<difficult>0</difficult>
		<bndbox>
			<xmin>447</xmin>
			<ymin>546</ymin>
			<xmax>753</xmax>
			<ymax>651</ymax>
		</bndbox>
	</object>
	<object>
		<name>Table</name>
		<pose>Unspecified</pose>
		<truncated>0</truncated>
		<difficult>0</difficult>
		<bndbox>
			<xmin>42</xmin>
			<ymin>524</ymin>
			<xmax>442</xmax>
			<ymax>669</ymax>
		</bndbox>
	</object>
	<object>
		<name>TextBox</name>
		<pose>Unspecified</pose>
		<truncated>0</truncated>
		<difficult>0</difficult>
		<bndbox>
			<xmin>70</xmin>
			<ymin>654</ymin>
			<xmax>737</xmax>
			<ymax>740</ymax>
		</bndbox>
	</object>
	<object>
		<name>TextBox</name>
		<pose>Unspecified</pose>
		<truncated>0</truncated>
		<difficult>0</difficult>
		<bndbox>
			<xmin>64</xmin>
			<ymin>873</ymin>
			<xmax>390</xmax>
			<ymax>917</ymax>
		</bndbox>
	</object>
	<object>
		<name>TextBox</name>
		<pose>Unspecified</pose>
		<truncated>0</truncated>
		<difficult>0</difficult>
		<bndbox>
			<xmin>62</xmin>
			<ymin>907</ymin>
			<xmax>511</xmax>
			<ymax>951</ymax>
		</bndbox>
	</object>
	<object>
		<name>TextBox</name>
		<pose>Unspecified</pose>
		<truncated>0</truncated>
		<difficult>0</difficult>
		<bndbox>
			<xmin>484</xmin>
			<ymin>1002</ymin>
			<xmax>620</xmax>
			<ymax>1030</ymax>
		</bndbox>
	</object>
	<object>
		<name>TextBox</name>
		<pose>Unspecified</pose>
		<truncated>0</truncated>
		<difficult>0</difficult>
		<bndbox>
			<xmin>448</xmin>
			<ymin>1034</ymin>
			<xmax>660</xmax>
			<ymax>1064</ymax>
		</bndbox>
	</object>
	<object>
		<name>TextBox</name>
		<pose>Unspecified</pose>
		<truncated>0</truncated>
		<difficult>0</difficult>
		<bndbox>
			<xmin>292</xmin>
			<ymin>980</ymin>
			<xmax>361</xmax>
			<ymax>1003</ymax>
		</bndbox>
	</object>
	<object>
		<name>TextBox</name>
		<pose>Unspecified</pose>
		<truncated>0</truncated>
		<difficult>0</difficult>
		<bndbox>
			<xmin>298</xmin>
			<ymin>1026</ymin>
			<xmax>353</xmax>
			<ymax>1042</ymax>
		</bndbox>
	</object>
	<object>
		<name>TextBox</name>
		<pose>Unspecified</pose>
		<truncated>0</truncated>
		<difficult>0</difficult>
		<bndbox>
			<xmin>50</xmin>
			<ymin>984</ymin>
			<xmax>204</xmax>
			<ymax>1011</ymax>
		</bndbox>
	</object>
	<object>
		<name>TextBox</name>
		<pose>Unspecified</pose>
		<truncated>0</truncated>
		<difficult>0</difficult>
		<bndbox>
			<xmin>88</xmin>
			<ymin>1015</ymin>
			<xmax>169</xmax>
			<ymax>1037</ymax>
		</bndbox>
	</object>
</annotation>
