<annotation>
	<folder>Images</folder>
	<filename>Invoice_500010_scaleGammaAddM25Rotate2.PNG</filename>
	<path>/home/pawel/PracaLocal/PRACA_LOCAL/OCR_AI/ocr-ai-preprocessing/SetUp_Manual_01/models/research/object_detection/synthDataAug/Images/Invoice_500010_scaleGammaAddM25Rotate2.PNG</path>
	<source>
		<database>Unknown</database>
	</source>
	<size>
		<width>794</width>
		<height>1123</height>
		<depth>3</depth>
	</size>
	<segmented>0</segmented>
	<object>
		<name>TextBox</name>
		<pose>Unspecified</pose>
		<truncated>0</truncated>
		<difficult>0</difficult>
		<bndbox>
			<xmin>66</xmin>
			<ymin>56</ymin>
			<xmax>302</xmax>
			<ymax>85</ymax>
		</bndbox>
	</object>
	<object>
		<name>TextBox</name>
		<pose>Unspecified</pose>
		<truncated>0</truncated>
		<difficult>0</difficult>
		<bndbox>
			<xmin>602</xmin>
			<ymin>85</ymin>
			<xmax>762</xmax>
			<ymax>122</ymax>
		</bndbox>
	</object>
	<object>
		<name>TextBox</name>
		<pose>Unspecified</pose>
		<truncated>0</truncated>
		<difficult>0</difficult>
		<bndbox>
			<xmin>66</xmin>
			<ymin>128</ymin>
			<xmax>142</xmax>
			<ymax>145</ymax>
		</bndbox>
	</object>
	<object>
		<name>TextBox</name>
		<pose>Unspecified</pose>
		<truncated>0</truncated>
		<difficult>0</difficult>
		<bndbox>
			<xmin>184</xmin>
			<ymin>130</ymin>
			<xmax>435</xmax>
			<ymax>186</ymax>
		</bndbox>
	</object>
	<object>
		<name>TextBox</name>
		<pose>Unspecified</pose>
		<truncated>0</truncated>
		<difficult>0</difficult>
		<bndbox>
			<xmin>648</xmin>
			<ymin>147</ymin>
			<xmax>757</xmax>
			<ymax>164</ymax>
		</bndbox>
	</object>
	<object>
		<name>TextBox</name>
		<pose>Unspecified</pose>
		<truncated>0</truncated>
		<difficult>0</difficult>
		<bndbox>
			<xmin>60</xmin>
			<ymin>234</ymin>
			<xmax>126</xmax>
			<ymax>252</ymax>
		</bndbox>
	</object>
	<object>
		<name>TextBox</name>
		<pose>Unspecified</pose>
		<truncated>0</truncated>
		<difficult>0</difficult>
		<bndbox>
			<xmin>182</xmin>
			<ymin>237</ymin>
			<xmax>449</xmax>
			<ymax>275</ymax>
		</bndbox>
	</object>
	<object>
		<name>TextBox</name>
		<pose>Unspecified</pose>
		<truncated>0</truncated>
		<difficult>0</difficult>
		<bndbox>
			<xmin>633</xmin>
			<ymin>255</ymin>
			<xmax>752</xmax>
			<ymax>274</ymax>
		</bndbox>
	</object>
	<object>
		<name>TextBox</name>
		<pose>Unspecified</pose>
		<truncated>0</truncated>
		<difficult>0</difficult>
		<bndbox>
			<xmin>60</xmin>
			<ymin>307</ymin>
			<xmax>106</xmax>
			<ymax>322</ymax>
		</bndbox>
	</object>
	<object>
		<name>TextBox</name>
		<pose>Unspecified</pose>
		<truncated>0</truncated>
		<difficult>0</difficult>
		<bndbox>
			<xmin>181</xmin>
			<ymin>309</ymin>
			<xmax>467</xmax>
			<ymax>335</ymax>
		</bndbox>
	</object>
	<object>
		<name>Table</name>
		<pose>Unspecified</pose>
		<truncated>0</truncated>
		<difficult>0</difficult>
		<bndbox>
			<xmin>46</xmin>
			<ymin>339</ymin>
			<xmax>748</xmax>
			<ymax>478</ymax>
		</bndbox>
	</object>
	<object>
		<name>Table</name>
		<pose>Unspecified</pose>
		<truncated>0</truncated>
		<difficult>0</difficult>
		<bndbox>
			<xmin>385</xmin>
			<ymin>467</ymin>
			<xmax>745</xmax>
			<ymax>571</ymax>
		</bndbox>
	</object>
	<object>
		<name>TextBox</name>
		<pose>Unspecified</pose>
		<truncated>0</truncated>
		<difficult>0</difficult>
		<bndbox>
			<xmin>74</xmin>
			<ymin>558</ymin>
			<xmax>421</xmax>
			<ymax>599</ymax>
		</bndbox>
	</object>
	<object>
		<name>TextBox</name>
		<pose>Unspecified</pose>
		<truncated>0</truncated>
		<difficult>0</difficult>
		<bndbox>
			<xmin>92</xmin>
			<ymin>702</ymin>
			<xmax>291</xmax>
			<ymax>733</ymax>
		</bndbox>
	</object>
	<object>
		<name>TextBox</name>
		<pose>Unspecified</pose>
		<truncated>0</truncated>
		<difficult>0</difficult>
		<bndbox>
			<xmin>431</xmin>
			<ymin>707</ymin>
			<xmax>621</xmax>
			<ymax>727</ymax>
		</bndbox>
	</object>
	<object>
		<name>TextBox</name>
		<pose>Unspecified</pose>
		<truncated>0</truncated>
		<difficult>0</difficult>
		<bndbox>
			<xmin>52</xmin>
			<ymin>766</ymin>
			<xmax>372</xmax>
			<ymax>804</ymax>
		</bndbox>
	</object>
	<object>
		<name>TextBox</name>
		<pose>Unspecified</pose>
		<truncated>0</truncated>
		<difficult>0</difficult>
		<bndbox>
			<xmin>565</xmin>
			<ymin>861</ymin>
			<xmax>677</xmax>
			<ymax>882</ymax>
		</bndbox>
	</object>
</annotation>
