<annotation>
	<folder>Images</folder>
	<filename>Invoice_300000_rotateM3_leftRight.PNG</filename>
	<path>/home/pawel/PracaLocal/PRACA_LOCAL/OCR_AI/ocr-ai-preprocessing/SetUp_Manual_01/models/research/object_detection/synthDataAug/Images/Invoice_300000_rotateM3_leftRight.PNG</path>
	<source>
		<database>Unknown</database>
	</source>
	<size>
		<width>794</width>
		<height>1123</height>
		<depth>3</depth>
	</size>
	<segmented>0</segmented>
	<object>
		<name>TextBox</name>
		<pose>Unspecified</pose>
		<truncated>0</truncated>
		<difficult>0</difficult>
		<bndbox>
			<xmin>514</xmin>
			<ymin>73</ymin>
			<xmax>722</xmax>
			<ymax>146</ymax>
		</bndbox>
	</object>
	<object>
		<name>Table</name>
		<pose>Unspecified</pose>
		<truncated>0</truncated>
		<difficult>0</difficult>
		<bndbox>
			<xmin>53</xmin>
			<ymin>542</ymin>
			<xmax>416</xmax>
			<ymax>683</ymax>
		</bndbox>
	</object>
	<object>
		<name>TextBox</name>
		<pose>Unspecified</pose>
		<truncated>0</truncated>
		<difficult>0</difficult>
		<bndbox>
			<xmin>343</xmin>
			<ymin>71</ymin>
			<xmax>436</xmax>
			<ymax>99</ymax>
		</bndbox>
	</object>
	<object>
		<name>TextBox</name>
		<pose>Unspecified</pose>
		<truncated>0</truncated>
		<difficult>0</difficult>
		<bndbox>
			<xmin>132</xmin>
			<ymin>74</ymin>
			<xmax>238</xmax>
			<ymax>107</ymax>
		</bndbox>
	</object>
	<object>
		<name>TextBox</name>
		<pose>Unspecified</pose>
		<truncated>0</truncated>
		<difficult>0</difficult>
		<bndbox>
			<xmin>166</xmin>
			<ymin>118</ymin>
			<xmax>215</xmax>
			<ymax>138</ymax>
		</bndbox>
	</object>
	<object>
		<name>TextBox</name>
		<pose>Unspecified</pose>
		<truncated>0</truncated>
		<difficult>0</difficult>
		<bndbox>
			<xmin>307</xmin>
			<ymin>120</ymin>
			<xmax>477</xmax>
			<ymax>158</ymax>
		</bndbox>
	</object>
	<object>
		<name>TextBox</name>
		<pose>Unspecified</pose>
		<truncated>0</truncated>
		<difficult>0</difficult>
		<bndbox>
			<xmin>201</xmin>
			<ymin>151</ymin>
			<xmax>269</xmax>
			<ymax>185</ymax>
		</bndbox>
	</object>
	<object>
		<name>TextBox</name>
		<pose>Unspecified</pose>
		<truncated>0</truncated>
		<difficult>0</difficult>
		<bndbox>
			<xmin>490</xmin>
			<ymin>179</ymin>
			<xmax>729</xmax>
			<ymax>245</ymax>
		</bndbox>
	</object>
	<object>
		<name>TextBox</name>
		<pose>Unspecified</pose>
		<truncated>0</truncated>
		<difficult>0</difficult>
		<bndbox>
			<xmin>49</xmin>
			<ymin>204</ymin>
			<xmax>379</xmax>
			<ymax>266</ymax>
		</bndbox>
	</object>
	<object>
		<name>TextBox</name>
		<pose>Unspecified</pose>
		<truncated>0</truncated>
		<difficult>0</difficult>
		<bndbox>
			<xmin>64</xmin>
			<ymin>271</ymin>
			<xmax>379</xmax>
			<ymax>332</ymax>
		</bndbox>
	</object>
	<object>
		<name>TextBox</name>
		<pose>Unspecified</pose>
		<truncated>0</truncated>
		<difficult>0</difficult>
		<bndbox>
			<xmin>487</xmin>
			<ymin>254</ymin>
			<xmax>733</xmax>
			<ymax>321</ymax>
		</bndbox>
	</object>
	<object>
		<name>Table</name>
		<pose>Unspecified</pose>
		<truncated>0</truncated>
		<difficult>0</difficult>
		<bndbox>
			<xmin>41</xmin>
			<ymin>318</ymin>
			<xmax>750</xmax>
			<ymax>561</ymax>
		</bndbox>
	</object>
	<object>
		<name>TextBox</name>
		<pose>Unspecified</pose>
		<truncated>0</truncated>
		<difficult>0</difficult>
		<bndbox>
			<xmin>486</xmin>
			<ymin>658</ymin>
			<xmax>754</xmax>
			<ymax>700</ymax>
		</bndbox>
	</object>
	<object>
		<name>TextBox</name>
		<pose>Unspecified</pose>
		<truncated>0</truncated>
		<difficult>0</difficult>
		<bndbox>
			<xmin>165</xmin>
			<ymin>680</ymin>
			<xmax>361</xmax>
			<ymax>710</ymax>
		</bndbox>
	</object>
	<object>
		<name>TextBox</name>
		<pose>Unspecified</pose>
		<truncated>0</truncated>
		<difficult>0</difficult>
		<bndbox>
			<xmin>398</xmin>
			<ymin>707</ymin>
			<xmax>756</xmax>
			<ymax>745</ymax>
		</bndbox>
	</object>
	<object>
		<name>TextBox</name>
		<pose>Unspecified</pose>
		<truncated>0</truncated>
		<difficult>0</difficult>
		<bndbox>
			<xmin>531</xmin>
			<ymin>770</ymin>
			<xmax>640</xmax>
			<ymax>802</ymax>
		</bndbox>
	</object>
	<object>
		<name>TextBox</name>
		<pose>Unspecified</pose>
		<truncated>0</truncated>
		<difficult>0</difficult>
		<bndbox>
			<xmin>168</xmin>
			<ymin>785</ymin>
			<xmax>301</xmax>
			<ymax>814</ymax>
		</bndbox>
	</object>
	<object>
		<name>TextBox</name>
		<pose>Unspecified</pose>
		<truncated>0</truncated>
		<difficult>0</difficult>
		<bndbox>
			<xmin>463</xmin>
			<ymin>811</ymin>
			<xmax>735</xmax>
			<ymax>859</ymax>
		</bndbox>
	</object>
	<object>
		<name>TextBox</name>
		<pose>Unspecified</pose>
		<truncated>0</truncated>
		<difficult>0</difficult>
		<bndbox>
			<xmin>103</xmin>
			<ymin>826</ymin>
			<xmax>422</xmax>
			<ymax>875</ymax>
		</bndbox>
	</object>
	<object>
		<name>TextBox</name>
		<pose>Unspecified</pose>
		<truncated>0</truncated>
		<difficult>0</difficult>
		<bndbox>
			<xmin>314</xmin>
			<ymin>938</ymin>
			<xmax>558</xmax>
			<ymax>979</ymax>
		</bndbox>
	</object>
	<object>
		<name>TextBox</name>
		<pose>Unspecified</pose>
		<truncated>0</truncated>
		<difficult>0</difficult>
		<bndbox>
			<xmin>507</xmin>
			<ymin>987</ymin>
			<xmax>752</xmax>
			<ymax>1019</ymax>
		</bndbox>
	</object>
	<object>
		<name>TextBox</name>
		<pose>Unspecified</pose>
		<truncated>0</truncated>
		<difficult>0</difficult>
		<bndbox>
			<xmin>125</xmin>
			<ymin>1011</ymin>
			<xmax>292</xmax>
			<ymax>1046</ymax>
		</bndbox>
	</object>
</annotation>
